{
  "name": "Disease",
  "fields": [
    {
      "fieldName": "name",
      "fieldType": "String"
    },
    {
      "fieldName": "description",
      "fieldType": "String"
    }
  ],
  "relationships": [],
  "changelogDate": "20201129143238",
  "javadoc": "Task entity.\\n@author The JHipster team.",
  "entityTableName": "disease",
  "dto": "mapstruct",
  "pagination": "pagination",
  "service": "serviceImpl",
  "jpaMetamodelFiltering": false,
  "fluentMethods": true,
  "readOnly": false,
  "embedded": false,
  "clientRootFolder": "",
  "applications": "*"
}
